flask_pluginkit/__init__.py
flask_pluginkit/_compat.py
flask_pluginkit/_installer.py
flask_pluginkit/_web.py
flask_pluginkit/exceptions.py
flask_pluginkit/pluginkit.py
flask_pluginkit/utils.py
flask_pluginkit/version.py
flask_pluginkit/static/translations.ini
flask_pluginkit/templates/manager.html
flask_pluginkit-3.10.1.dist-info/licenses/LICENSE
flask_pluginkit-3.10.1.dist-info/METADATA
flask_pluginkit-3.10.1.dist-info/WHEEL
flask_pluginkit-3.10.1.dist-info/top_level.txt
flask_pluginkit-3.10.1.dist-info/RECORD
