Metadata-Version: 2.4
Name: Flask-PluginKit
Version: 3.10.1
Summary: Load and run plugins for your Flask application
Home-page: https://github.com/staugur/Flask-PluginKit
Download-URL: https://github.com/staugur/Flask-PluginKit/releases/tag/v3.10.1
Author: Hiroshi.tao
Author-email: me@tcw.im
License: BSD 3-Clause
Project-URL: Code, https://github.com/staugur/Flask-PluginKit
Project-URL: Issue tracker, https://github.com/staugur/Flask-PluginKit/issues
Project-URL: Documentation, https://flask-pluginkit.rtfd.vip
Keywords: flask plugin
Classifier: Development Status :: 4 - Beta
Classifier: Framework :: Flask
Classifier: Environment :: Web Environment
Classifier: Intended Audience :: Developers
Classifier: License :: OSI Approved :: BSD License
Classifier: Operating System :: OS Independent
Classifier: Programming Language :: Python :: 3
Classifier: Programming Language :: Python :: 3.8
Classifier: Programming Language :: Python :: 3.9
Classifier: Programming Language :: Python :: 3.10
Classifier: Programming Language :: Python :: 3.11
Classifier: Programming Language :: Python :: Implementation :: CPython
Classifier: Topic :: Internet :: WWW/HTTP :: Dynamic Content
Classifier: Topic :: Software Development :: Libraries :: Python Modules
Requires-Python: >=3.8
License-File: LICENSE
Requires-Dist: Flask>=3.0.0
Requires-Dist: semver>=3.0.0
Provides-Extra: redis
Requires-Dist: redis>=5.0.0; extra == "redis"
Dynamic: author
Dynamic: author-email
Dynamic: classifier
Dynamic: description
Dynamic: download-url
Dynamic: home-page
Dynamic: keywords
Dynamic: license
Dynamic: license-file
Dynamic: project-url
Dynamic: provides-extra
Dynamic: requires-dist
Dynamic: requires-python
Dynamic: summary
